{"is_source_file": false, "format": "", "description": "", "external_files": [], "external_methods": [], "published": [], "classes": [], "methods": [], "calls": [], "search-terms": [], "state": 2, "file_id": 5, "knowledge_revision": 10, "git_revision": "e1c1b2d9726c4a305e71ff1db8ca2395fb50140f", "hash": "b584d8936b91a01f13a45c2252449033", "format-version": 4, "code-base-name": "tic_tac_toe_backend", "filename": "tic_tac_toe_backend/Properties/launchSettings.json", "revision_history": [{"10": "e1c1b2d9726c4a305e71ff1db8ca2395fb50140f"}]}